pyexcel_webio/__init__.py
pyexcel_webio-0.1.4.dist-info/DESCRIPTION.rst
pyexcel_webio-0.1.4.dist-info/METADATA
pyexcel_webio-0.1.4.dist-info/RECORD
pyexcel_webio-0.1.4.dist-info/WHEEL
pyexcel_webio-0.1.4.dist-info/metadata.json
pyexcel_webio-0.1.4.dist-info/top_level.txt
